annotationframeworkclient/__init__.py
annotationframeworkclient/annotationengine.py
annotationframeworkclient/auth.py
annotationframeworkclient/base.py
annotationframeworkclient/chunkedgraph.py
annotationframeworkclient/emannotationschemas.py
annotationframeworkclient/endpoints.py
annotationframeworkclient/format_utils.py
annotationframeworkclient/frameworkclient.py
annotationframeworkclient/infoservice.py
annotationframeworkclient/jsonservice.py
annotationframeworkclient/materializationengine.py
annotationframeworkclient-2.9.1.dist-info/METADATA
annotationframeworkclient-2.9.1.dist-info/WHEEL
annotationframeworkclient-2.9.1.dist-info/top_level.txt
annotationframeworkclient-2.9.1.dist-info/RECORD
