Metadata-Version: 2.1
Name: annotationframeworkclient
Version: 2.9.1
Summary: a service for interacting with the AnnotationFramework
Home-page: https://github.com/seung-lab/AnnotationFrameworkClient
Author: Sven Dorkenwald
Author-email: svenmd@princeton.edu
License: UNKNOWN
Platform: UNKNOWN
Requires-Dist: numpy
Requires-Dist: pyarrow (>=3)
Requires-Dist: requests
Requires-Dist: sqlalchemy
Requires-Dist: pandas
